README.rst
setup.cfg
setup.py
django_pnm.egg-info/PKG-INFO
django_pnm.egg-info/SOURCES.txt
django_pnm.egg-info/dependency_links.txt
django_pnm.egg-info/not-zip-safe
django_pnm.egg-info/pbr.json
django_pnm.egg-info/requires.txt
django_pnm.egg-info/top_level.txt
push_notifications/__init__.py
push_notifications/admin.py
push_notifications/models.py
push_notifications/serializers.py
push_notifications/urls.py
push_notifications/utils.py
push_notifications/views.py
push_notifications/migrations/0001_initial.py
push_notifications/migrations/0002_auto_20150528_1115.py
push_notifications/migrations/__init__.py
push_notifications/services/__init__.py
push_notifications/services/base.py
push_notifications/services/exceptions.py
push_notifications/services/zeropush.py