Metadata-Version: 1.1
Name: django-pnm
Version: 0.1.6
Summary: A plug and play package to handle push devices and push notifications for services such as ZeroPush and Urban Airship
Home-page: https://github.com/Fueled/django-push-notifications
Author: Paul Oostenrijk
Author-email: paul@glemma.nl
License: BSD
Keywords: pnm,django,push,notifications,manager
Platform: UNKNOWN
Classifier: Development Status :: 2 - Pre-Alpha
Classifier: Framework :: Django
Classifier: Intended Audience :: Developers
Classifier: License :: OSI Approved :: BSD License
Classifier: Natural Language :: English
Classifier: Programming Language :: Python :: 2
Classifier: Programming Language :: Python :: 2.6
Classifier: Programming Language :: Python :: 2.7
Classifier: Programming Language :: Python :: 3
Classifier: Programming Language :: Python :: 3.3
